MANIFEST.in
README.rst
setup.cfg
setup.py
docs/HISTORY.rst
docs/INSTALL.rst
docs/LICENSE.GPL
docs/LICENSE.txt
platocdp/__init__.py
platocdp.newsportlet.egg-info/PKG-INFO
platocdp.newsportlet.egg-info/SOURCES.txt
platocdp.newsportlet.egg-info/dependency_links.txt
platocdp.newsportlet.egg-info/entry_points.txt
platocdp.newsportlet.egg-info/namespace_packages.txt
platocdp.newsportlet.egg-info/not-zip-safe
platocdp.newsportlet.egg-info/paster_plugins.txt
platocdp.newsportlet.egg-info/requires.txt
platocdp.newsportlet.egg-info/top_level.txt
platocdp/newsportlet/__init__.py
platocdp/newsportlet/configure.zcml
platocdp/newsportlet/interfaces.py
platocdp/newsportlet/setuphandlers.py
platocdp/newsportlet/behavior/README.txt
platocdp/newsportlet/behavior/__init__.py
platocdp/newsportlet/behavior/configure.zcml
platocdp/newsportlet/browser/README.txt
platocdp/newsportlet/browser/__init__.py
platocdp/newsportlet/content/README.txt
platocdp/newsportlet/content/__init__.py
platocdp/newsportlet/locales/README.txt
platocdp/newsportlet/portlet/__init__.py
platocdp/newsportlet/portlet/configure.zcml
platocdp/newsportlet/portlet/newsportlet.py
platocdp/newsportlet/portlet/templates/newsportlet.pt
platocdp/newsportlet/profiles/default/browserlayer.xml
platocdp/newsportlet/profiles/default/cssregistry.xml
platocdp/newsportlet/profiles/default/jsregistry.xml
platocdp/newsportlet/profiles/default/metadata.xml
platocdp/newsportlet/profiles/default/platocdp.newsportlet.marker.txt
platocdp/newsportlet/profiles/default/portlets.xml
platocdp/newsportlet/profiles/default/types.xml
platocdp/newsportlet/schemaextender/__init__.py
platocdp/newsportlet/static/README.txt
platocdp/newsportlet/upgrades/__init__.py
platocdp/newsportlet/upgrades/handlers.py
platocdp/newsportlet/upgrades/profiles.py
platocdp/newsportlet/viewlet/__init__.py
platocdp/newsportlet/vocabulary/__init__.py