Metadata-Version: 1.1
Name: platocdp.newsportlet
Version: 1.0a1
Summary: Portlets for News Item contents
Home-page: http://github.com/koslab/platocdp.newsportlet
Author: KOSLAB Technologies
Author-email: izhar@koslab.org
License: GPLv2+
Platform: UNKNOWN
Classifier: Framework :: Plone
Classifier: Programming Language :: Python
Classifier: Topic :: Software Development :: Libraries :: Python Modules
